[
  {
    "id": "gie_boat",
    "name": {
      "en": "Venice of the North",
      "tr": "Kuzeyin Venediği"
    },
    "description": {
      "en": "No roads, just canals: Boat tour and thatched-roof cottages",
      "tr": "Yol yok, sadece kanallar: Tekne turu ve saz çatılı evler."
    },
    "duration": {
      "en": "3 hours",
      "tr": "3 saat"
    },
    "distance": "3 km",
    "difficulty": {
      "en": "Easy",
      "tr": "Kolay"
    },
    "imageUrl": "https://storage.googleapis.com/myway-3fe75.firebasestorage.app/cities/giethoorn/giethoorn_canals.jpg",
    "tags": {
      "en": "Boat",
      "tr": "Tekne"
    },
    "placeNames": [
      "Giethoorn Canals",
      "Museum Giethoorn 't Olde Maat Uus",
      "Binnenpad (Walking Path)",
      "Smit's Paviljoen (Lunch)"
    ],
    "interests": [
      "Doğa",
      "Huzur",
      "Yemek"
    ],
    "accentColor": "0xFF2980B9"
  }
]